pyflow_manager/__init__.py
pyflow_manager/pyflow_manager.py
tests/__init__.py
tests/sample_task.py
tests/sample_task2.py
tests/test_pyflow_manager.py
pyflow_manager-0.3.2.dist-info/LICENSE
pyflow_manager-0.3.2.dist-info/METADATA
pyflow_manager-0.3.2.dist-info/WHEEL
pyflow_manager-0.3.2.dist-info/entry_points.txt
pyflow_manager-0.3.2.dist-info/top_level.txt
pyflow_manager-0.3.2.dist-info/RECORD
