Metadata-Version: 2.1
Name: pyflow_manager
Version: 0.3.2
Summary: A workflow management system based on YAML dependencies
Home-page: https://github.com/HuzeyfeAyaz/pyflow_manager
Author: Huzeyfe Ayaz
Author-email: huzeyfeayaz23@gmail.com
Classifier: Programming Language :: Python :: 3
Classifier: License :: OSI Approved :: MIT License
Classifier: Operating System :: OS Independent
Requires-Python: >=3.6
License-File: LICENSE
Requires-Dist: pyyaml
Requires-Dist: networkx
Provides-Extra: dev
Requires-Dist: pytest ; extra == 'dev'
